LICENSE
MANIFEST.in
README.rst
setup.py
keyless_fernet/__init__.py
keyless_fernet/core.py
keyless_fernet.egg-info/PKG-INFO
keyless_fernet.egg-info/SOURCES.txt
keyless_fernet.egg-info/dependency_links.txt
keyless_fernet.egg-info/pbr.json
keyless_fernet.egg-info/top_level.txt
keyless_fernet/tests/__init__.py
keyless_fernet/tests/test_token.py