Metadata-Version: 1.1
Name: keyless-fernet
Version: 1.0.0
Summary: Parse Fernet tokens as much as possible without using a key.
Home-page: http://github.com/dolph/keyless-fernet
Author: Dolph Mathews
Author-email: dolph.mathews@gmail.com
License: UNKNOWN
Platform: UNKNOWN
Classifier: Development Status :: 5 - Production/Stable
Classifier: Intended Audience :: Developers
Classifier: Topic :: Security
Classifier: Topic :: Software Development :: Libraries
